{
  "dct_title_s": "Maurice River near Taylors Ditch",
  "dct_description_sm": [
    "Map shows a portion of the Maurice River near Taylors Ditch. Shows the high and low water lines, bearings, and Richard W. Robbins Marsh. There are 7 acres of marsh."
  ],
  "dct_language_sm": [
    "eng"
  ],
  "schema_provider_s": "Rutgers University-New Brunswick",
  "gbl_resourceClass_sm": [
    "Maps"
  ],
  "dct_subject_sm": [
    "New Jersey Environmental Digital Library"
  ],
  "dcat_keyword_sm": [
    "IIIF active",
    "Tidelands",
    "Geographic Information Systems",
    "metadataSprint_2022-11--Mercer County--Cumberland County"
  ],
  "dct_issued_s": "1900",
  "gbl_indexYear_im": [
    "1900"
  ],
  "gbl_dateRange_drsim": [
    "[1900 TO 1900]"
  ],
  "dct_spatial_sm": [
    "New Jersey--Mercer County",
    "New Jersey--Cumberland County",
    "New Jersey"
  ],
  "locn_geometry": "POLYGON((-75.444751 39.568746, -74.851794 39.568746, -74.851794 39.056179, -75.444751 39.056179, -75.444751 39.568746))",
  "dcat_bbox": "ENVELOPE(-75.444751,-74.851794,39.568746,39.056179)",
  "dcat_centroid": "39.312462499999995,-75.14827249999999",
  "pcdm_memberOf_sm": [
    "64bd8c4c-8e60-4956-b43d-bdc3f93db488"
  ],
  "dct_isPartOf_sm": [
    "14d-01"
  ],
  "dct_rights_sm": [
    "This resource may be copyright protected. You may make use of this resource, with proper attribution, for educational and other non-commercial uses only. Contact the contributing organization to obtain permission for reproduction, publication, and commercial use."
  ],
  "dct_rightsHolder_sm": [
    "Rutgers University Libraries"
  ],
  "dct_accessRights_s": "Public",
  "dct_format_s": "PDF",
  "dct_references_s": "{\"http://schema.org/url\":\"https://rucore.libraries.rutgers.edu/rutgers-lib/56659\",\"http://schema.org/downloadUrl\":[{\"label\":\"PDF\",\"url\":\"https://rucore.libraries.rutgers.edu/rutgers-lib/56659/PDF/1/play/\"}]}",
  "id": "rutgers-lib:56659",
  "dct_identifier_sm": [
    "https://doi.org/doi:10.7282/T3X06BBC"
  ],
  "gbl_mdModified_dt": "2023-03-14T19:52:40Z",
  "gbl_mdVersion_s": "Aardvark"
}